csv_split/__init__.py
csv_split/splitter.py
csv_split-0.1.2.data/scripts/csv-split
csv_split-0.1.2.dist-info/LICENSE
csv_split-0.1.2.dist-info/METADATA
csv_split-0.1.2.dist-info/WHEEL
csv_split-0.1.2.dist-info/top_level.txt
csv_split-0.1.2.dist-info/RECORD
