Metadata-Version: 2.1
Name: csv-split
Version: 0.1.2
Summary: A cli tool to split csv files
Home-page: https://github.com/bilal-fazlani/splitcsv
Author: Bilal Fazlani
Author-email: bilal.m.fazlani@gmail.com
License: UNKNOWN
Keywords: csv file split bilal-fazlani
Platform: UNKNOWN
Classifier: Programming Language :: Python :: 3
Classifier: License :: OSI Approved :: MIT License
Classifier: Operating System :: OS Independent
Requires-Python: >=3.7
